spacy_curated_transformers/__init__.py
spacy_curated_transformers/_compat.py
spacy_curated_transformers/schedules.py
spacy_curated_transformers/util.py
spacy_curated_transformers/cli/__init__.py
spacy_curated_transformers/cli/debug_pieces.py
spacy_curated_transformers/cli/fill_config_transformer.py
spacy_curated_transformers/models/__init__.py
spacy_curated_transformers/models/architectures.py
spacy_curated_transformers/models/hf_loader.py
spacy_curated_transformers/models/listeners.py
spacy_curated_transformers/models/output.py
spacy_curated_transformers/models/pooling.py
spacy_curated_transformers/models/remove_eos_bos.py
spacy_curated_transformers/models/scalar_weight.py
spacy_curated_transformers/models/types.py
spacy_curated_transformers/models/with_non_ws_tokens.py
spacy_curated_transformers/models/with_strided_spans.py
spacy_curated_transformers/models/pytorch/__init__.py
spacy_curated_transformers/models/pytorch/scalar_weight.py
spacy_curated_transformers/pipeline/__init__.py
spacy_curated_transformers/pipeline/transformer.py
spacy_curated_transformers/tests/__init__.py
spacy_curated_transformers/tests/conftest.py
spacy_curated_transformers/tests/enable_gpu.py
spacy_curated_transformers/tests/test_cli_app.py
spacy_curated_transformers/tests/test_registry.py
spacy_curated_transformers/tests/test_schedules.py
spacy_curated_transformers/tests/test_torchscript_wrapper.py
spacy_curated_transformers/tests/util.py
spacy_curated_transformers/tests/models/__init__.py
spacy_curated_transformers/tests/models/test_hf_model.py
spacy_curated_transformers/tests/models/test_listeners.py
spacy_curated_transformers/tests/models/test_pooling.py
spacy_curated_transformers/tests/models/test_scalar_weight.py
spacy_curated_transformers/tests/models/test_transformer_model.py
spacy_curated_transformers/tests/models/test_with_non_ws_tokens.py
spacy_curated_transformers/tests/models/test_with_strided_spans.py
spacy_curated_transformers/tests/pipeline/__init__.py
spacy_curated_transformers-2.0.0.dist-info/LICENSE
spacy_curated_transformers-2.0.0.dist-info/METADATA
spacy_curated_transformers-2.0.0.dist-info/WHEEL
spacy_curated_transformers-2.0.0.dist-info/entry_points.txt
spacy_curated_transformers-2.0.0.dist-info/top_level.txt
spacy_curated_transformers-2.0.0.dist-info/zip-safe
spacy_curated_transformers-2.0.0.dist-info/RECORD
