Metadata-Version: 2.1
Name: spacy-curated-transformers
Version: 2.0.0
Summary: Curated transformer models for spaCy pipelines
Home-page: https://github.com/explosion/spacy-curated-transformers
Author: Explosion
Author-email: contact@explosion.ai
License: MIT
Requires-Python: >=3.9
License-File: LICENSE
Requires-Dist: curated-transformers<3.0.0,>=2.0.0
Requires-Dist: curated-tokenizers<3.0.0,>=2.0.0
Requires-Dist: fsspec>=2023.5.0
Requires-Dist: spacy<5.0.0,>=4.0.0.dev2
Requires-Dist: thinc<9.1.0,>=9.0.0.dev4
Requires-Dist: torch>=1.12.0
